{
    "site_key_color": "#40FFFF",
    "site_key_text_color": "#004646",
    "site_text_color": "#0F0F0F",
    "site_background_color": "#E0FFFF",
    "site_selection_color": "#0000ff",
    "site_selection_background_color": "#bcebeb",
    "site_link_color": "#cc8f00",
    "header_container_background_color": "#00FFFF",
    "header_container_text_color": "#ffffff",
    "header_background_color": "#00FFFF",
    "header_text_color": "#004646",
    "global_navi_background_color": "#40FFFF",
    "global_navi_text_color": "#004646",
    "notice_area_background_color": "#80FFFF",
    "notice_area_text_color": "#004646",
    "appeal_area_background_color": "#A0FFFF",
    "appeal_area_button_background_color": "#00bfff",
    "footer_background_color": "#40FFFF",
    "footer_text_color": "#004646",
    "go_to_top_background_color": "#E0FFFF",
    "go_to_top_text_color": "#40FFFF",
    "editor_background_color": "",
    "editor_text_color": "",
    "block_editor_extended_palette_color_a": "#E0FFFF",
    "block_editor_extended_palette_color_b": "#C0FFFF",
    "block_editor_extended_palette_color_c": "#A0FFFF",
    "block_editor_extended_palette_color_d": "#80FFFF",
    "block_editor_extended_palette_color_e": "#40FFFF",
    "block_editor_extended_palette_color_f": "#00FFFF",
    "main_column_border_color": "",
    "sidebar_border_color": "#C0FFFF",
    "color_description": "",
    "color_name": "cyan"
}